pyTOPSScrape/__init__.py
pyTOPSScrape/api/__init__.py
pyTOPSScrape/api/api.py
pyTOPSScrape/api/convert.py
pyTOPSScrape/api/utils.py
pyTOPSScrape/err/__init__.py
pyTOPSScrape/err/err.py
pyTOPSScrape/misc/__init__.py
pyTOPSScrape/misc/utils.py
pyTOPSScrape/misc/dataFiles/__init__.py
pyTOPSScrape/misc/dataFiles/nonRectProfile.npy
pyTOPSScrape/parse/__init__.py
pyTOPSScrape/parse/abundance.py
pyTOPSScrape/parse/opal.py
pyTOPSScrape/parse/tops.py
pyTOPSScrape/scripts/__init__.py
pyTOPSScrape/scripts/generateTOPStables.py
pyTOPSScrape/scripts/main.py
pytopsscrape-1.1.dist-info/licenses/LICENSE.md
pytopsscrape-1.1.dist-info/METADATA
pytopsscrape-1.1.dist-info/WHEEL
pytopsscrape-1.1.dist-info/entry_points.txt
pytopsscrape-1.1.dist-info/top_level.txt
pytopsscrape-1.1.dist-info/RECORD
