Metadata-Version: 2.4
Name: pyTOPSScrape
Version: 1.1
Summary: Python bindings around TOPS webform for OPLIB opacities
Author-email: "Emily M. Boudreaux" <emily@boudreauxmail.com>
Project-URL: Homepage, https://github.com/tboudreaux/pytopsscrape
Classifier: Programming Language :: Python
Classifier: Operating System :: MacOS :: MacOS X
Classifier: Operating System :: POSIX :: Linux
Classifier: Topic :: Scientific/Engineering :: Astronomy
Requires-Python: >=3.8
License-File: LICENSE.md
Requires-Dist: mechanize>=0.4.5
Requires-Dist: numpy>=1.19.2
Requires-Dist: scipy>=1.5.2
Requires-Dist: importlib_resources>=5.2.0
Requires-Dist: tqdm>=4.50.2
Requires-Dist: beautifulsoup4>=4.9.3
Requires-Dist: pip-system-certs
Dynamic: license-file
